cpsvis/__init__.py
cpsvis/main.py
cpsvis-0.0.21.dist-info/LICENSE
cpsvis-0.0.21.dist-info/METADATA
cpsvis-0.0.21.dist-info/WHEEL
cpsvis-0.0.21.dist-info/top_level.txt
cpsvis-0.0.21.dist-info/RECORD
