Metadata-Version: 2.1
Name: cpsvis
Version: 0.0.21
Summary: Convex Projective Surface Visualisation Tool
Home-page: https://github.com/sepehrsaryazdi/cpsvis2
Author: Sepehr Saryazdi
Author-email: sepehr.saryazdi@gmail.com
License: MIT
Platform: UNKNOWN
Classifier: License :: OSI Approved :: MIT License
Classifier: Programming Language :: Python :: 3.10
Classifier: Operating System :: OS Independent
Requires-Python: >=3.8
Requires-Dist: matplotlib (>=3.5.2)
Requires-Dist: numpy (>=1.21.5)
Provides-Extra: dev
Requires-Dist: pytest (>=7.0) ; extra == 'dev'
Requires-Dist: twine (>=4.0.2) ; extra == 'dev'
